traitlets/__init__.py
traitlets/_version.py
traitlets/log.py
traitlets/py.typed
traitlets/traitlets.py
traitlets/config/__init__.py
traitlets/config/application.py
traitlets/config/argcomplete_config.py
traitlets/config/configurable.py
traitlets/config/loader.py
traitlets/config/manager.py
traitlets/config/sphinxdoc.py
traitlets/tests/__init__.py
traitlets/tests/test_traitlets.py
traitlets/tests/utils.py
traitlets/utils/__init__.py
traitlets/utils/bunch.py
traitlets/utils/decorators.py
traitlets/utils/descriptions.py
traitlets/utils/getargspec.py
traitlets/utils/importstring.py
traitlets/utils/nested_update.py
traitlets/utils/sentinel.py
traitlets/utils/text.py
traitlets/utils/warnings.py
traitlets-5.11.0.dist-info/METADATA
traitlets-5.11.0.dist-info/WHEEL
traitlets-5.11.0.dist-info/licenses/LICENSE
traitlets-5.11.0.dist-info/RECORD
