Metadata-Version: 2.1
Name: traitlets
Version: 5.11.0
Summary: Traitlets Python configuration system
Project-URL: Homepage, https://github.com/ipython/traitlets
Author-email: IPython Development Team <ipython-dev@python.org>
License: BSD 3-Clause License
License-File: LICENSE
Keywords: Interactive,Interpreter,Shell,Web
Classifier: Intended Audience :: Developers
Classifier: Intended Audience :: Science/Research
Classifier: Intended Audience :: System Administrators
Classifier: License :: OSI Approved :: BSD License
Classifier: Programming Language :: Python
Classifier: Programming Language :: Python :: 3
Requires-Python: >=3.8
Provides-Extra: docs
Requires-Dist: myst-parser; extra == 'docs'
Requires-Dist: pydata-sphinx-theme; extra == 'docs'
Requires-Dist: sphinx; extra == 'docs'
Provides-Extra: test
Requires-Dist: argcomplete>=3.0.3; extra == 'test'
Requires-Dist: mypy>=1.5.1; extra == 'test'
Requires-Dist: pre-commit; extra == 'test'
Requires-Dist: pytest-mock; extra == 'test'
Requires-Dist: pytest-mypy-testing; extra == 'test'
Requires-Dist: pytest<7.5,>=7.0; extra == 'test'
